LICENSE.txt
README.md
setup.py
Topsis/Topsis.py
Topsis_Noordeep_102017145.egg-info/PKG-INFO
Topsis_Noordeep_102017145.egg-info/SOURCES.txt
Topsis_Noordeep_102017145.egg-info/dependency_links.txt
Topsis_Noordeep_102017145.egg-info/entry_points.txt
Topsis_Noordeep_102017145.egg-info/requires.txt
Topsis_Noordeep_102017145.egg-info/top_level.txt