Metadata-Version: 2.1
Name: Topsis-Noordeep-102017145
Version: 1.0.0.2
Summary: A Python package for handling problems of Multiple Criteria Decision Making(MCDM) for a given dataset.
Author: Noordeep Kaur
Author-email: noordeep29oct@gmail.com
License: MIT
Classifier: Development Status :: 3 - Alpha
Classifier: Intended Audience :: Developers
Classifier: Topic :: Software Development :: Build Tools
Classifier: License :: OSI Approved :: MIT License
Classifier: Programming Language :: Python :: 3.6
Classifier: Programming Language :: Python :: 3.7
Classifier: Programming Language :: Python :: 3.8
License-File: LICENSE.txt
